sliceitoff/__main__.py
sliceitoff/assets/8x8.fnt
sliceitoff/assets/COPYRIGHTS.txt
sliceitoff/assets/baby.mp3
sliceitoff/assets/fonts.lst
sliceitoff/assets/glass.mp3
sliceitoff/assets/laser.mp3
sliceitoff/assets/lcd.fnt
sliceitoff/assets/pimpelipompeli.mp3
sliceitoff/assets/uhkapeli.mp3
sliceitoff/display/__init__.py
sliceitoff/display/display.py
sliceitoff/display/scaling.py
sliceitoff/display/static.py
sliceitoff/enemies/__init__.py
sliceitoff/enemies/ball.py
sliceitoff/enemies/bouncher.py
sliceitoff/enemies/enemies.py
sliceitoff/enemies/enemy.py
sliceitoff/field/__init__.py
sliceitoff/field/field.py
sliceitoff/game/__init__.py
sliceitoff/game/game.py
sliceitoff/game/gameplay.py
sliceitoff/game/level.py
sliceitoff/hiscores/__init__.py
sliceitoff/hiscores/hiscores.py
sliceitoff/hiscores/static.py
sliceitoff/main.py
sliceitoff/menu/__init__.py
sliceitoff/menu/anykey.py
sliceitoff/menu/explodeout.py
sliceitoff/menu/initials.py
sliceitoff/menu/mainmenu.py
sliceitoff/menu/menu.py
sliceitoff/menu/settings.py
sliceitoff/menu/show.py
sliceitoff/player/__init__.py
sliceitoff/player/life.py
sliceitoff/player/player.py
sliceitoff/player/static.py
sliceitoff/screens/__init__.py
sliceitoff/screens/gameover.py
sliceitoff/screens/hiscores.py
sliceitoff/screens/initials.py
sliceitoff/screens/instructions1.py
sliceitoff/screens/instructions2.py
sliceitoff/screens/level.py
sliceitoff/screens/levelup.py
sliceitoff/screens/mainmenu.py
sliceitoff/screens/settings.py
sliceitoff/settings/__init__.py
sliceitoff/settings/settings.py
sliceitoff/settings/static.py
sliceitoff/sfx/__init__.py
sliceitoff/sfx/sfx.py
sliceitoff/stats/__init__.py
sliceitoff/stats/stats.py
sliceitoff/status/__init__.py
sliceitoff/status/status.py
sliceitoff/text/__init__.py
sliceitoff/text/explode.py
sliceitoff/text/fonts.py
sliceitoff/text/text.py
sliceitoff-0.4.post1.dist-info/LICENSE.txt
sliceitoff-0.4.post1.dist-info/METADATA
sliceitoff-0.4.post1.dist-info/WHEEL
sliceitoff-0.4.post1.dist-info/entry_points.txt
sliceitoff-0.4.post1.dist-info/RECORD
