Metadata-Version: 2.1
Name: sliceitoff
Version: 0.4.post1
Summary: Arcade game where one slices play area off while avoiding slicing happy faces.
Home-page: https://git.hix.fi/sliceitoff.git/
Author: Viljami Ilola
Author-email: +@hix.fi
Requires-Python: >=3.10,<4.0
Classifier: Programming Language :: Python :: 3
Classifier: Programming Language :: Python :: 3.10
Classifier: Programming Language :: Python :: 3.11
Classifier: Programming Language :: Python :: 3.12
Requires-Dist: pygame (>=2.5.2,<3.0.0)
Project-URL: Repository, https://git.hix.fi/sliceitoff.git/
